psychopy_usbToBNC/__init__.py
psychopy_usbToBNC/usbToBNC/__init__.py
psychopy1_usbToBNC-0.0.2.dist-info/LICENSE
psychopy1_usbToBNC-0.0.2.dist-info/METADATA
psychopy1_usbToBNC-0.0.2.dist-info/WHEEL
psychopy1_usbToBNC-0.0.2.dist-info/entry_points.txt
psychopy1_usbToBNC-0.0.2.dist-info/top_level.txt
psychopy1_usbToBNC-0.0.2.dist-info/RECORD
