Metadata-Version: 2.1
Name: psychopy1-usbToBNC
Version: 0.0.2
Summary: Coming soon
Home-page: UNKNOWN
Author: Labeo Technologies(Christophe Cloutier-Tremblay)
Author-email: <Christophe@labeotech.com>
License: UNKNOWN
Keywords: python
Platform: UNKNOWN
Classifier: Development Status :: 1 - Planning
Classifier: Intended Audience :: Science/Research
Classifier: Programming Language :: Python :: 3
Classifier: Operating System :: Unix
Classifier: Operating System :: MacOS :: MacOS X
Classifier: Operating System :: Microsoft :: Windows
Requires-Dist: Psychopy
